sgframework/__init__.py
sgframework/langchain/__init__.py
sgframework/langchain/logging.py
sgframework/langchain/document/__init__.py
sgframework/langchain/document/info.py
sgframework/mcp/__init__.py
sgframework/mcp/load_config.py
sgframework/utils/__init__.py
sgframework/utils/dict_util.py
sgframework/utils/file_util.py
sgframework/utils/string_util.py
py_sgframework-0.1.10.dist-info/METADATA
py_sgframework-0.1.10.dist-info/WHEEL
py_sgframework-0.1.10.dist-info/top_level.txt
py_sgframework-0.1.10.dist-info/RECORD
