Metadata-Version: 2.4
Name: py-sgframework
Version: 0.1.10
Summary: sgFramework Python Library
Requires-Python: >=3.13
Requires-Dist: langchain>=0.3.27
Requires-Dist: langchain-mcp-adapters>=0.1.9
